MANIFEST.in
README.md
VERSION.txt
requirements.txt
requirements_dev.txt
setup.cfg
setup.py
csh_sanitizer/__init__.py
csh_sanitizer/definitions.py
csh_sanitizer/encoder.py
csh_sanitizer/mark_iterencode.py
csh_sanitizer/sanitizer.py
csh_sanitizer.egg-info/PKG-INFO
csh_sanitizer.egg-info/SOURCES.txt
csh_sanitizer.egg-info/dependency_links.txt
csh_sanitizer.egg-info/not-zip-safe
csh_sanitizer.egg-info/requires.txt
csh_sanitizer.egg-info/top_level.txt