Metadata-Version: 2.1
Name: csh-sanitizer
Version: 1.0.0
Summary: Convert basic HTML into JSON format.
Home-page: https://github.com/sunil-reglobe/csh-sanitizer
Author: Sunil Kumar
License: UNKNOWN
Platform: UNKNOWN
Classifier: Programming Language :: Python
Classifier: Environment :: Web Environment
Classifier: Intended Audience :: Developers
Classifier: Topic :: Software Development :: Libraries :: Python Modules
Provides-Extra: dev
